README.md
setup.py
ai_platform_iscas/__init__.py
ai_platform_iscas/dataset.py
ai_platform_iscas/model.py
ai_platform_iscas.egg-info/PKG-INFO
ai_platform_iscas.egg-info/SOURCES.txt
ai_platform_iscas.egg-info/dependency_links.txt
ai_platform_iscas.egg-info/top_level.txt